kuva_geometry/__init__.py
kuva_geometry/constants.py
kuva_geometry/ellipsoid.py
kuva_geometry/geometry.py
kuva_geometry-1.0.3.dist-info/METADATA
kuva_geometry-1.0.3.dist-info/WHEEL
kuva_geometry-1.0.3.dist-info/RECORD
