Metadata-Version: 2.4
Name: kuva-geometry
Version: 1.0.3
Summary: Definitions and helper functionalities for Kuva Space geometric operations
Author-email: Guillem Ballesteros <guillem@kuvaspace.com>, Lennert Antson <lennert.antson@kuvaspace.com>, Arthur Vandenhoeke <arthur.vandenhoeke@kuvaspace.com>, Olli Eloranta <olli.eloranta@kuvaspace.com>
License-Expression: MIT
Requires-Python: <=3.13,>=3.10
Requires-Dist: numpy-quaternion>=2022.4.4
Requires-Dist: numpy>=1.26.4
Requires-Dist: pint<1.0.0,>=0.22
Requires-Dist: sympy<2.0.0,>=1.13.3
